vpi/vpi_console/vpi_console.sv
module vpi_console (
    input aclk,
    input aresetn,
    
    // Interface to CPU (Memory-Mapped Registers)
    output reg rx_intr,                 
    output [$clog2(BUFFER_DEPTH):0] rx_fill_level, 
    
    // CPU Buffer Read Interface (Read/Dequeue operation)
    output wire [7:0] rx_buffer_data_out, 
    input wire rx_buffer_read_strobe,     
    
    // VPI Interface 
    input wire [7:0] tx_data_in,
    input wire tx_data_valid 
);

// --- VPI System Task/Function Declarations (Corrected) ---

// FIX: $vpi_getc is a FUNCTION and must be declared as such.

// --- Local Parameters and Constants ---
parameter BUFFER_DEPTH = 1024;
localparam ASCII_BACKSPACE = 8'h08;
localparam ASCII_ENTER     = 8'h0A;
localparam ASCII_CR        = 8'h0D;
localparam ASCII_MONEY     = 8'h24;
localparam ASCII_MOUSE     = 8'h40;

// --- Buffer Registers (Circular Buffer) ---
reg [7:0] line_buffer [0:BUFFER_DEPTH-1];
reg [9:0] head_ptr; 
reg [9:0] tail_ptr; 

// --- Internal Control Registers ---
reg rx_data_available; 
reg [7:0] rx_char;
reg [9:0] next_tail_ptr;

// --- AXI/CPU Interface Wires ---
wire [10:0] calculated_fill;
assign calculated_fill = (tail_ptr >= head_ptr) ? (tail_ptr - head_ptr) : (BUFFER_DEPTH - head_ptr + tail_ptr);

assign rx_fill_level = calculated_fill[10:0]; 

assign rx_buffer_data_out = line_buffer[head_ptr];

// --- VPI Polling Logic ---
reg [3:0] rx_poll_counter = 0;
localparam POLL_RATE = 0;
reg [31:0] char_code_reg; // Receives output from $vpi_getc

always @(posedge aclk) begin
    if (!aresetn) begin
        rx_poll_counter <= 0;
        rx_data_available <= 1'b0;
    end else begin
        rx_poll_counter <= rx_poll_counter + 1;
        
        if (rx_poll_counter == POLL_RATE) begin
            rx_poll_counter <= 0;
            
            // FIX: Call the VPI Function and assign its return value
            char_code_reg = $vpi_getc(1); 
            
            if (char_code_reg != 0) begin
                rx_char <= char_code_reg[7:0];
                rx_data_available <= 1'b1;
            end
        end else if (rx_data_available) begin
            rx_data_available <= 1'b0;
        end
    end
end

// --- RX Buffer and Line-Editing Logic ---
always @(posedge aclk) begin
    if (!aresetn) begin
        head_ptr <= 0;
        tail_ptr <= 0;
        rx_intr <= 1'b0;
    end else begin
        
        // --- Dequeue Logic (CPU Read) ---
        if (rx_buffer_read_strobe && (head_ptr != tail_ptr)) begin
            head_ptr <= head_ptr + 1;
            if (head_ptr == BUFFER_DEPTH - 1) head_ptr <= 0;

            if (rx_fill_level == 1) rx_intr <= 1'b0;
        end

        // --- Enqueue/Edit Logic (VPI Write) ---
        if (rx_data_available) begin
            
            next_tail_ptr = tail_ptr + 1;
            if (tail_ptr == BUFFER_DEPTH - 1) next_tail_ptr = 0;

            if (rx_char == ASCII_ENTER) begin
                if (calculated_fill > 0) begin
                    line_buffer[tail_ptr] <= rx_char;
                    tail_ptr <= next_tail_ptr;
                    rx_intr <= 1'b1;
                end
                $vpi_putc(ASCII_ENTER);// Space
                $display("Receive Enter!\n");
            end else if (rx_char == ASCII_BACKSPACE) begin
                if (calculated_fill > 0) begin
                    tail_ptr <= (tail_ptr == 0) ? (BUFFER_DEPTH - 1) : tail_ptr - 1;
                    
                    $vpi_putc(ASCII_BACKSPACE);
                    $vpi_putc(8'h20); // Space
                    $vpi_putc(ASCII_BACKSPACE);
                end
                rx_intr <= 0;
            end else if (next_tail_ptr != head_ptr) begin 
                line_buffer[tail_ptr] <= rx_char;
                tail_ptr <= next_tail_ptr;
                $vpi_putc(rx_char);
                rx_intr <= 0;
            end  else begin
                $vpi_putc(8'h07); // ASCII Bell
                rx_intr <= 0;
            end
        end else begin
            rx_intr <= 0;
        end
    end
end

// --- TX Logic (Simple Pass-through for Bi-directionality) ---
always @(posedge aclk) begin
    if (tx_data_valid) begin
        $vpi_putc(tx_data_in); 
    end
end

endmodule

vpi/vpi_console/console_tb.sv
`timescale 1ns / 100ps

module testbench_console;

    // --- Clock and Reset Signals ---
    reg aclk;
    reg aresetn;
    reg start;

    // --- Signals for CPU Interface (RX/Input from Host) ---
    wire rx_intr;
    wire [10:0] rx_fill_level; 
    wire [7:0] rx_buffer_data_out;
    reg rx_buffer_read_strobe;

    // --- Signals for CPU Interface (TX/Output to Host) ---
    reg tx_data_valid;
    reg [7:0] tx_data_in; // Signal driven by the task to the DUT's input port

    // Instantiate the DUT (vpi_console)
    vpi_console #(
        .BUFFER_DEPTH(1024)
    ) DUT (
        .aclk(aclk),
        .aresetn(aresetn),

        .rx_intr(rx_intr),
        .rx_fill_level(rx_fill_level),
        .rx_buffer_data_out(rx_buffer_data_out),
        .rx_buffer_read_strobe(rx_buffer_read_strobe),
        
        .tx_data_valid(tx_data_valid),
        .tx_data_in(tx_data_in) // Connects to the DUT's tx_data_in port
    );
    
    // --- Clock Generation ---
    initial begin
        aclk = 0;
        forever #5 aclk = ~aclk; // 10ns period (100 MHz)
    end

    // --- TX Task: Sends an ASCII string to the VPI Console ---
    task tx_string;
        input [8*256-1:0] message; 
        input integer message_length;
        integer i;
        reg [7:0] char_code;
        begin
            for (i = 0; i < message_length; i = i + 1) begin
                char_code = message[8*i +: 8]; 
                
                tx_data_in = char_code; 
                tx_data_valid = 1;
                @(posedge aclk);
                tx_data_valid = 0;
                #50; // Delay to simulate CPU clock cycles
            end
        end
    endtask

    // --- RX Task: Reads the complete buffered command ---
    task read_buffer;
        input [9:0] length; 
        integer i;
        reg [7:0] data;
        begin
            for (i = 0; i < length; i = i + 1) begin
                @(posedge aclk);
                
                rx_buffer_read_strobe = 1;
                data = rx_buffer_data_out; 
                
                @(posedge aclk);
                rx_buffer_read_strobe = 0;
                
                if (data != 8'h00)
                    $display("    Byte %0d: ENTER (0x%h)", i, data);
                else
                    $display("    Byte %0d: '%c' (0x%h)", i, data, data);

                #50;
            end
        end
    endtask
    
    // --- Infinite Test Scenario ---
    initial begin
        $dumpfile("./my_simulation.vcd");
        $dumpvars(0, DUT);
        // 1. Reset and Initialization
        aresetn = 0;
        rx_buffer_read_strobe = 0;
        tx_data_valid = 0;
        #100 aresetn = 1;

        // 2. Transmit Initialization Message
        $display("-------------------------------------------------------");
        $display("   [Testbench] Console Interactive Mode Initialized.");
        $display("   Type 'Ctrl+D' to quit the simulation.");
        $display("-------------------------------------------------------");
        
        #50;
        tx_string("Welcome to the CPU Console VIP!\n", 30);
        tx_string("Enter command:\n> ", 18);
        
        // 3. Main Operational Loop (Runs until $finish is called by C code)
        forever begin
            
            // Wait for the CPU to be interrupted (User presses Enter)
            @(posedge aclk);
            if(rx_intr)begin
            	$display("\n-------------------------------------------------------");
            	$display("   [Testbench] RX INTERRUPT RECEIVED! Command Ready.");
            	$display("   Fill Level: %0d bytes", rx_fill_level);
            	$display("-------------------------------------------------------");
            
            	// 4. Simulate CPU reading the buffer
            	read_buffer(rx_fill_level);
            
            	// 5. Provide a response and prompt for the next command
            	tx_string("Command processed. Ready for next command:\n> ", 44);
            end
        end
        
        // Execution will terminate only when vpi_control(vpiFinish) is called by C code
    end
    
    
    
endmodule

vpi/vip_console/my_simulation.vcd
$date
	Wed Dec 10 16:50:33 2025
$end
$version
	Icarus Verilog
$end
$timescale
	100ps
$end
$scope module testbench_console $end
$scope module DUT $end
$var wire 1 ! aclk $end
$var wire 1 " aresetn $end
$var wire 8 # rx_buffer_data_out [7:0] $end
$var wire 1 $ rx_buffer_read_strobe $end
$var wire 11 % rx_fill_level [10:0] $end
$var wire 8 & tx_data_in [7:0] $end
$var wire 1 ' tx_data_valid $end
$var wire 11 ( calculated_fill [10:0] $end
$var reg 32 ) char_code_reg [31:0] $end
$var reg 10 * head_ptr [9:0] $end
$var reg 10 + next_tail_ptr [9:0] $end
$var reg 8 , rx_char [7:0] $end
$var reg 1 - rx_data_available $end
$var reg 1 . rx_intr $end
$var reg 4 / rx_poll_counter [3:0] $end
$var reg 10 0 tail_ptr [9:0] $end
$upscope $end
$upscope $end
$enddefinitions $end
#0
$dumpvars
bx 0
b0 /
x.
x-
bx ,
bx +
bx *
bx )
bx (
0'
bx &
bx %
0$
bx #
0"
0!
$end
#50
b0 %
b0 (
0-
0.
b0 0
b0 *
1!
#100
0!
#150
1!
#200
0!
#250
1!
#300
0!
#350
1!
#400
0!
#450
1!
#500
0!
#550
1!
#600
0!
#650
1!
#700
0!
#750
1!
#800
0!
#850
1!
#900
0!
#950
1!
#1000
0!
1"
#1050
1-
b110001 ,
b0 /
b110001 )
1!
#1100
0!
#1150
b1 %
b1 (
b1 0
b110001 #
b110010 ,
b0 /
b1 +
b110010 )
1!
#1200
0!
#1250
b10 %
b10 (
b110011 ,
b0 /
b10 0
b110011 )
b10 +
1!
#1300
0!
#1350
b11 %
b11 (
b11 0
b110100 ,
b0 /
b11 +
b110100 )
1!
#1400
0!
#1450
b100 %
b100 (
b110101 ,
b0 /
b100 0
b110101 )
b100 +
1!
#1500
0!
1'
b1010 &
#1550
b101 %
b101 (
b101 0
b110110 ,
b0 /
b101 +
b110110 )
0'
1!
#1600
0!
#1650
b110 %
b110 (
b110111 ,
b0 /
b110 0
b110111 )
b110 +
1!
#1700
0!
#1750
b111 %
b111 (
b111 0
b111000 ,
b0 /
b111 +
b111000 )
1!
#1800
0!
#1850
b1000 %
b1000 (
b111001 ,
b0 /
b1000 0
b111001 )
b1000 +
1!
#1900
0!
#1950
b1001 %
b1001 (
b1001 0
b0 /
b1001 +
1!
#2000
0!
#2050
b1010 %
b1010 (
b110001 ,
b0 /
b1010 0
b110001 )
b1010 +
1!
0'
b100001 &
#2100
0!
#2150
b1011 %
b1011 (
b1011 0
b110010 ,
b0 /
b1011 +
b110010 )
1!
#2200
0!
#2250
b1100 %
b1100 (
b110011 ,
b0 /
b1100 0
b110011 )
b1100 +
1!
#2300
0!
#2350
b1101 %
b1101 (
b1101 0
b110100 ,
b0 /
b1101 +
b110100 )
1!
#2400
0!
#2450
b1110 %
b1110 (
b110101 ,
b0 /
b1110 0
b110101 )
b1110 +
1!
#2500
0!
#2550
b1111 %
b1111 (
b1111 0
b110110 ,
b0 /
b1111 +
b110110 )
1!
0'
b1010000 &
#2600
0!
#2650
b10000 %
b10000 (
b110111 ,
b0 /
b10000 0
b110111 )
b10000 +
1!
#2700
0!
#2750
b10001 %
b10001 (
b10001 0
b111000 ,
b0 /
b10001 +
b111000 )
1!
#2800
0!
#2850
b10010 %
b10010 (
b111001 ,
b0 /
b10010 0
b111001 )
b10010 +
1!
#2900
0!
#2950
b10011 %
b10011 (
b10011 0
b1010 ,
b0 /
b10011 +
b1010 )
1!
#3000
0!
#3050
b10100 %
b10100 (
b0 /
1.
b10100 0
b10100 +
1!
0'
b1001001 &
